vacasa/__init__.py
vacasa/api.py
vacasa-0.0.1.dist-info/METADATA
vacasa-0.0.1.dist-info/RECORD
vacasa-0.0.1.dist-info/WHEEL
vacasa-0.0.1.dist-info/top_level.txt
