Metadata-Version: 2.1
Name: vacasa
Version: 0.0.1
Summary: A Python client for the Vacasa Connect API
Home-page: https://github.com/johnwmillr/VacasaConnectAPI
Author: John W. Miller
License: MIT
Keywords: vacasa API home rental vacation property reality
Platform: UNKNOWN
Classifier: Topic :: Software Development :: Libraries
Classifier: Operating System :: OS Independent
Classifier: Programming Language :: Python
Classifier: Programming Language :: Python :: 3
Requires-Python: >=3.*
Requires-Dist: requests
